LICENSE.txt
MANIFEST.in
README.rst
setup.py
FBBack/__init__.py
FBBack/client.py
FBBack/models.py
FBBack/stickers.py
FBBack/utils.py
FBBack.egg-info/PKG-INFO
FBBack.egg-info/SOURCES.txt
FBBack.egg-info/dependency_links.txt
FBBack.egg-info/requires.txt
FBBack.egg-info/top_level.txt
FBBack.egg-info/zip-safe